{"ranking":[{"name":"Argentina","value":193699},{"name":"Bolivia","value":75739},{"name":"Chile","value":135590},{"name":"Colombia","value":143584},{"name":"Dominican Rep.","value":40425},{"name":"Ecuador","value":90883},{"name":"El Salvador","value":47293},{"name":"Guatemala","value":82348},{"name":"Honduras","value":33691},{"name":"Mexico","value":150024},{"name":"Panama","value":31631},{"name":"Paraguay","value":57372},{"name":"Perú","value":125226},{"name":"Spain","value":407859},{"name":"Uruguay","value":88921},{"name":"Venezuela","value":113674}]}
